LICENSE
logistics_or_gym/__init__.py
logistics_or_gym/envs/HeterogeneousCVRP.py
logistics_or_gym/envs/__init__.py
logistics_or_gym-0.10.0.dist-info/LICENSE
logistics_or_gym-0.10.0.dist-info/METADATA
logistics_or_gym-0.10.0.dist-info/WHEEL
logistics_or_gym-0.10.0.dist-info/RECORD
