Metadata-Version: 2.1
Name: logistics_or_gym
Version: 0.10.0
Summary: or-problems formulated as gym environments to solve logisitcal-problems
Home-page: https://github.com/HublyGroup/logistics-or-gym
License: MIT
Keywords: logistics-or-gym,or,gym,logistics,logistics-or,or-gym
Author: hadisdev
Author-email: hadi.salameh@hotmail.com
Requires-Python: >=3.10,<3.12
Classifier: Development Status :: 2 - Pre-Alpha
Classifier: License :: OSI Approved :: MIT License
Classifier: Operating System :: OS Independent
Classifier: Programming Language :: Python :: 3
Classifier: Programming Language :: Python :: 3.10
Classifier: Programming Language :: Python :: 3.11
Requires-Dist: gymnasium (>=0.29.1,<1)
Requires-Dist: numpy (>=1.25.2,<2)
Requires-Dist: setuptools (>=68.1.2,<69.0.0)
Project-URL: Repository, https://github.com/HublyGroup/logistics-or-gym
